{
    "Loaded": true,
    "Name": "Knightspath",
    "RegionName": "Tulune",
    "HasDungeon": false,
    "MapTableData": {
        "MapId": 760000000293,
        "Latitude": 21912,
        "Longitude": 37520,
        "LocationType": 1,
        "DungeonType": 255,
        "Discovered": true,
        "Key": 18882816
    },
    "Exterior": {
        "RecordElement": {
            "Header": {
                "X": 9609216,
                "Y": 24913921,
                "IsExterior": 32768,
                "Unknown2": 69,
                "LocationId": 17409,
                "IsInterior": 0,
                "ExteriorLocationId": 0,
                "LocationName": "Knightspath"
            }
        },
        "BuildingCount": 122,
        "Buildings": [
            {
                "NameSeed": 17820,
                "FactionId": 0,
                "Sector": 29,
                "LocationId": 17409,
                "BuildingType": 18,
                "Quality": 9
            },
            {
                "NameSeed": 23606,
                "FactionId": 0,
                "Sector": 35,
                "LocationId": 17409,
                "BuildingType": 18,
                "Quality": 16
            },
            {
                "NameSeed": 26263,
                "FactionId": 0,
                "Sector": 39,
                "LocationId": 17409,
                "BuildingType": 18,
                "Quality": 2
            },
            {
                "NameSeed": 15973,
                "FactionId": 0,
                "Sector": 49,
                "LocationId": 17409,
                "BuildingType": 18,
                "Quality": 16
            },
            {
                "NameSeed": 2380,
                "FactionId": 0,
                "Sector": 60,
                "LocationId": 17409,
                "BuildingType": 18,
                "Quality": 7
            },
            {
                "NameSeed": 9233,
                "FactionId": 0,
                "Sector": 65,
                "LocationId": 17409,
                "BuildingType": 18,
                "Quality": 5
            },
            {
                "NameSeed": 15670,
                "FactionId": 0,
                "Sector": 73,
                "LocationId": 17409,
                "BuildingType": 18,
                "Quality": 6
            },
            {
                "NameSeed": 12022,
                "FactionId": 0,
                "Sector": 80,
                "LocationId": 17409,
                "BuildingType": 18,
                "Quality": 7
            },
            {
                "NameSeed": 14370,
                "FactionId": 0,
                "Sector": 89,
                "LocationId": 17409,
                "BuildingType": 18,
                "Quality": 16
            },
            {
                "NameSeed": 10922,
                "FactionId": 0,
                "Sector": 93,
                "LocationId": 17409,
                "BuildingType": 18,
                "Quality": 9
            },
            {
                "NameSeed": 236,
                "FactionId": 0,
                "Sector": 97,
                "LocationId": 17409,
                "BuildingType": 18,
                "Quality": 9
            },
            {
                "NameSeed": 14737,
                "FactionId": 0,
                "Sector": 102,
                "LocationId": 17409,
                "BuildingType": 18,
                "Quality": 8
            },
            {
                "NameSeed": 17616,
                "FactionId": 108,
                "Sector": 108,
                "LocationId": 17409,
                "BuildingType": 18,
                "Quality": 8
            },
            {
                "NameSeed": 26513,
                "FactionId": 510,
                "Sector": 138,
                "LocationId": 17409,
                "BuildingType": 15,
                "Quality": 11
            },
            {
                "NameSeed": 10546,
                "FactionId": 0,
                "Sector": 151,
                "LocationId": 17409,
                "BuildingType": 19,
                "Quality": 6
            },
            {
                "NameSeed": 32478,
                "FactionId": 0,
                "Sector": 156,
                "LocationId": 17409,
                "BuildingType": 18,
                "Quality": 2
            },
            {
                "NameSeed": 7846,
                "FactionId": 0,
                "Sector": 162,
                "LocationId": 17409,
                "BuildingType": 18,
                "Quality": 13
            },
            {
                "NameSeed": 12644,
                "FactionId": 0,
                "Sector": 170,
                "LocationId": 17409,
                "BuildingType": 18,
                "Quality": 10
            },
            {
                "NameSeed": 12240,
                "FactionId": 0,
                "Sector": 173,
                "LocationId": 17409,
                "BuildingType": 18,
                "Quality": 1
            },
            {
                "NameSeed": 10366,
                "FactionId": 0,
                "Sector": 179,
                "LocationId": 17409,
                "BuildingType": 19,
                "Quality": 20
            },
            {
                "NameSeed": 2791,
                "FactionId": 0,
                "Sector": 184,
                "LocationId": 17409,
                "BuildingType": 18,
                "Quality": 15
            },
            {
                "NameSeed": 14385,
                "FactionId": 0,
                "Sector": 189,
                "LocationId": 17409,
                "BuildingType": 18,
                "Quality": 15
            },
            {
                "NameSeed": 30131,
                "FactionId": 0,
                "Sector": 197,
                "LocationId": 17409,
                "BuildingType": 18,
                "Quality": 9
            },
            {
                "NameSeed": 21030,
                "FactionId": 42,
                "Sector": 202,
                "LocationId": 17409,
                "BuildingType": 18,
                "Quality": 6
            },
            {
                "NameSeed": 15771,
                "FactionId": 510,
                "Sector": 220,
                "LocationId": 17409,
                "BuildingType": 15,
                "Quality": 12
            },
            {
                "NameSeed": 19258,
                "FactionId": 0,
                "Sector": 235,
                "LocationId": 17409,
                "BuildingType": 18,
                "Quality": 13
            },
            {
                "NameSeed": 916,
                "FactionId": 0,
                "Sector": 241,
                "LocationId": 17409,
                "BuildingType": 18,
                "Quality": 12
            },
            {
                "NameSeed": 32080,
                "FactionId": 0,
                "Sector": 247,
                "LocationId": 17409,
                "BuildingType": 18,
                "Quality": 4
            },
            {
                "NameSeed": 8038,
                "FactionId": 0,
                "Sector": 256,
                "LocationId": 17409,
                "BuildingType": 18,
                "Quality": 18
            },
            {
                "NameSeed": 8431,
                "FactionId": 0,
                "Sector": 263,
                "LocationId": 17409,
                "BuildingType": 18,
                "Quality": 7
            },
            {
                "NameSeed": 24831,
                "FactionId": 0,
                "Sector": 268,
                "LocationId": 17409,
                "BuildingType": 18,
                "Quality": 19
            },
            {
                "NameSeed": 27680,
                "FactionId": 0,
                "Sector": 274,
                "LocationId": 17409,
                "BuildingType": 18,
                "Quality": 10
            },
            {
                "NameSeed": 25986,
                "FactionId": 0,
                "Sector": 279,
                "LocationId": 17409,
                "BuildingType": 18,
                "Quality": 9
            },
            {
                "NameSeed": 32367,
                "FactionId": 0,
                "Sector": 285,
                "LocationId": 17409,
                "BuildingType": 18,
                "Quality": 18
            },
            {
                "NameSeed": 7577,
                "FactionId": 0,
                "Sector": 297,
                "LocationId": 17409,
                "BuildingType": 18,
                "Quality": 19
            },
            {
                "NameSeed": 9737,
                "FactionId": 0,
                "Sector": 301,
                "LocationId": 17409,
                "BuildingType": 18,
                "Quality": 3
            },
            {
                "NameSeed": 31223,
                "FactionId": 0,
                "Sector": 306,
                "LocationId": 17409,
                "BuildingType": 18,
                "Quality": 3
            },
            {
                "NameSeed": 29863,
                "FactionId": 0,
                "Sector": 316,
                "LocationId": 17409,
                "BuildingType": 18,
                "Quality": 3
            },
            {
                "NameSeed": 26023,
                "FactionId": 0,
                "Sector": 325,
                "LocationId": 17409,
                "BuildingType": 18,
                "Quality": 9
            },
            {
                "NameSeed": 1217,
                "FactionId": 0,
                "Sector": 335,
                "LocationId": 17409,
                "BuildingType": 18,
                "Quality": 14
            },
            {
                "NameSeed": 12520,
                "FactionId": 0,
                "Sector": 340,
                "LocationId": 17409,
                "BuildingType": 18,
                "Quality": 19
            },
            {
                "NameSeed": 29349,
                "FactionId": 0,
                "Sector": 349,
                "LocationId": 17409,
                "BuildingType": 18,
                "Quality": 19
            },
            {
                "NameSeed": 14533,
                "FactionId": 0,
                "Sector": 359,
                "LocationId": 17409,
                "BuildingType": 18,
                "Quality": 16
            },
            {
                "NameSeed": 9927,
                "FactionId": 0,
                "Sector": 363,
                "LocationId": 17409,
                "BuildingType": 18,
                "Quality": 16
            },
            {
                "NameSeed": 1349,
                "FactionId": 0,
                "Sector": 367,
                "LocationId": 17409,
                "BuildingType": 18,
                "Quality": 10
            },
            {
                "NameSeed": 32703,
                "FactionId": 0,
                "Sector": 372,
                "LocationId": 17409,
                "BuildingType": 18,
                "Quality": 7
            },
            {
                "NameSeed": 11554,
                "FactionId": 510,
                "Sector": 379,
                "LocationId": 17409,
                "BuildingType": 15,
                "Quality": 1
            },
            {
                "NameSeed": 29566,
                "FactionId": 510,
                "Sector": 391,
                "LocationId": 17409,
                "BuildingType": 15,
                "Quality": 17
            },
            {
                "NameSeed": 19684,
                "FactionId": 0,
                "Sector": 407,
                "LocationId": 17409,
                "BuildingType": 19,
                "Quality": 9
            },
            {
                "NameSeed": 26453,
                "FactionId": 0,
                "Sector": 412,
                "LocationId": 17409,
                "BuildingType": 18,
                "Quality": 15
            },
            {
                "NameSeed": 28904,
                "FactionId": 0,
                "Sector": 418,
                "LocationId": 17409,
                "BuildingType": 18,
                "Quality": 20
            },
            {
                "NameSeed": 27403,
                "FactionId": 0,
                "Sector": 425,
                "LocationId": 17409,
                "BuildingType": 18,
                "Quality": 17
            },
            {
                "NameSeed": 1367,
                "FactionId": 0,
                "Sector": 429,
                "LocationId": 17409,
                "BuildingType": 18,
                "Quality": 10
            },
            {
                "NameSeed": 32615,
                "FactionId": 0,
                "Sector": 433,
                "LocationId": 17409,
                "BuildingType": 18,
                "Quality": 8
            },
            {
                "NameSeed": 22597,
                "FactionId": 0,
                "Sector": 440,
                "LocationId": 17409,
                "BuildingType": 18,
                "Quality": 2
            },
            {
                "NameSeed": 2398,
                "FactionId": 0,
                "Sector": 447,
                "LocationId": 17409,
                "BuildingType": 18,
                "Quality": 1
            },
            {
                "NameSeed": 29328,
                "FactionId": 0,
                "Sector": 457,
                "LocationId": 17409,
                "BuildingType": 18,
                "Quality": 14
            },
            {
                "NameSeed": 8665,
                "FactionId": 0,
                "Sector": 466,
                "LocationId": 17409,
                "BuildingType": 18,
                "Quality": 3
            },
            {
                "NameSeed": 30682,
                "FactionId": 0,
                "Sector": 471,
                "LocationId": 17409,
                "BuildingType": 18,
                "Quality": 14
            },
            {
                "NameSeed": 27361,
                "FactionId": 0,
                "Sector": 478,
                "LocationId": 17409,
                "BuildingType": 18,
                "Quality": 7
            },
            {
                "NameSeed": 13984,
                "FactionId": 510,
                "Sector": 483,
                "LocationId": 17409,
                "BuildingType": 15,
                "Quality": 10
            },
            {
                "NameSeed": 6168,
                "FactionId": 0,
                "Sector": 507,
                "LocationId": 17409,
                "BuildingType": 19,
                "Quality": 13
            },
            {
                "NameSeed": 24151,
                "FactionId": 0,
                "Sector": 513,
                "LocationId": 17409,
                "BuildingType": 18,
                "Quality": 16
            },
            {
                "NameSeed": 27162,
                "FactionId": 0,
                "Sector": 519,
                "LocationId": 17409,
                "BuildingType": 18,
                "Quality": 4
            },
            {
                "NameSeed": 9341,
                "FactionId": 0,
                "Sector": 526,
                "LocationId": 17409,
                "BuildingType": 18,
                "Quality": 12
            },
            {
                "NameSeed": 7696,
                "FactionId": 0,
                "Sector": 529,
                "LocationId": 17409,
                "BuildingType": 18,
                "Quality": 4
            },
            {
                "NameSeed": 14537,
                "FactionId": 0,
                "Sector": 535,
                "LocationId": 17409,
                "BuildingType": 18,
                "Quality": 8
            },
            {
                "NameSeed": 4716,
                "FactionId": 0,
                "Sector": 542,
                "LocationId": 17409,
                "BuildingType": 18,
                "Quality": 1
            },
            {
                "NameSeed": 12339,
                "FactionId": 0,
                "Sector": 549,
                "LocationId": 17409,
                "BuildingType": 18,
                "Quality": 16
            },
            {
                "NameSeed": 10249,
                "FactionId": 0,
                "Sector": 555,
                "LocationId": 17409,
                "BuildingType": 18,
                "Quality": 3
            },
            {
                "NameSeed": 4242,
                "FactionId": 0,
                "Sector": 560,
                "LocationId": 17409,
                "BuildingType": 18,
                "Quality": 10
            },
            {
                "NameSeed": 12628,
                "FactionId": 0,
                "Sector": 568,
                "LocationId": 17409,
                "BuildingType": 18,
                "Quality": 18
            },
            {
                "NameSeed": 5446,
                "FactionId": 0,
                "Sector": 573,
                "LocationId": 17409,
                "BuildingType": 18,
                "Quality": 16
            },
            {
                "NameSeed": 26850,
                "FactionId": 510,
                "Sector": 576,
                "LocationId": 17409,
                "BuildingType": 9,
                "Quality": 10
            },
            {
                "NameSeed": 3814,
                "FactionId": 510,
                "Sector": 587,
                "LocationId": 17409,
                "BuildingType": 9,
                "Quality": 9
            },
            {
                "NameSeed": 22665,
                "FactionId": 0,
                "Sector": 599,
                "LocationId": 17409,
                "BuildingType": 19,
                "Quality": 8
            },
            {
                "NameSeed": 5374,
                "FactionId": 0,
                "Sector": 604,
                "LocationId": 17409,
                "BuildingType": 18,
                "Quality": 8
            },
            {
                "NameSeed": 26266,
                "FactionId": 0,
                "Sector": 610,
                "LocationId": 17409,
                "BuildingType": 18,
                "Quality": 6
            },
            {
                "NameSeed": 17144,
                "FactionId": 0,
                "Sector": 617,
                "LocationId": 17409,
                "BuildingType": 18,
                "Quality": 19
            },
            {
                "NameSeed": 30723,
                "FactionId": 0,
                "Sector": 621,
                "LocationId": 17409,
                "BuildingType": 18,
                "Quality": 6
            },
            {
                "NameSeed": 6476,
                "FactionId": 0,
                "Sector": 628,
                "LocationId": 17409,
                "BuildingType": 18,
                "Quality": 12
            },
            {
                "NameSeed": 17727,
                "FactionId": 0,
                "Sector": 635,
                "LocationId": 17409,
                "BuildingType": 18,
                "Quality": 18
            },
            {
                "NameSeed": 3060,
                "FactionId": 0,
                "Sector": 641,
                "LocationId": 17409,
                "BuildingType": 18,
                "Quality": 9
            },
            {
                "NameSeed": 32481,
                "FactionId": 0,
                "Sector": 646,
                "LocationId": 17409,
                "BuildingType": 18,
                "Quality": 14
            },
            {
                "NameSeed": 11396,
                "FactionId": 0,
                "Sector": 655,
                "LocationId": 17409,
                "BuildingType": 18,
                "Quality": 11
            },
            {
                "NameSeed": 9664,
                "FactionId": 510,
                "Sector": 658,
                "LocationId": 17409,
                "BuildingType": 9,
                "Quality": 1
            },
            {
                "NameSeed": 29862,
                "FactionId": 510,
                "Sector": 669,
                "LocationId": 17409,
                "BuildingType": 9,
                "Quality": 20
            },
            {
                "NameSeed": 17384,
                "FactionId": 510,
                "Sector": 681,
                "LocationId": 17409,
                "BuildingType": 5,
                "Quality": 5
            },
            {
                "NameSeed": 17641,
                "FactionId": 510,
                "Sector": 690,
                "LocationId": 17409,
                "BuildingType": 5,
                "Quality": 2
            },
            {
                "NameSeed": 11472,
                "FactionId": 0,
                "Sector": 695,
                "LocationId": 17409,
                "BuildingType": 18,
                "Quality": 19
            },
            {
                "NameSeed": 9552,
                "FactionId": 0,
                "Sector": 701,
                "LocationId": 17409,
                "BuildingType": 18,
                "Quality": 10
            },
            {
                "NameSeed": 275,
                "FactionId": 0,
                "Sector": 708,
                "LocationId": 17409,
                "BuildingType": 18,
                "Quality": 9
            },
            {
                "NameSeed": 9153,
                "FactionId": 0,
                "Sector": 714,
                "LocationId": 17409,
                "BuildingType": 18,
                "Quality": 8
            },
            {
                "NameSeed": 26984,
                "FactionId": 0,
                "Sector": 720,
                "LocationId": 17409,
                "BuildingType": 18,
                "Quality": 6
            },
            {
                "NameSeed": 28712,
                "FactionId": 0,
                "Sector": 729,
                "LocationId": 17409,
                "BuildingType": 18,
                "Quality": 14
            },
            {
                "NameSeed": 18806,
                "FactionId": 0,
                "Sector": 736,
                "LocationId": 17409,
                "BuildingType": 18,
                "Quality": 11
            },
            {
                "NameSeed": 15971,
                "FactionId": 0,
                "Sector": 741,
                "LocationId": 17409,
                "BuildingType": 18,
                "Quality": 8
            },
            {
                "NameSeed": 5917,
                "FactionId": 0,
                "Sector": 747,
                "LocationId": 17409,
                "BuildingType": 18,
                "Quality": 13
            },
            {
                "NameSeed": 1995,
                "FactionId": 0,
                "Sector": 753,
                "LocationId": 17409,
                "BuildingType": 18,
                "Quality": 6
            },
            {
                "NameSeed": 113,
                "FactionId": 510,
                "Sector": 759,
                "LocationId": 17409,
                "BuildingType": 15,
                "Quality": 2
            },
            {
                "NameSeed": 20146,
                "FactionId": 41,
                "Sector": 782,
                "LocationId": 17409,
                "BuildingType": 11,
                "Quality": 2
            },
            {
                "NameSeed": 16188,
                "FactionId": 0,
                "Sector": 789,
                "LocationId": 17409,
                "BuildingType": 18,
                "Quality": 3
            },
            {
                "NameSeed": 12268,
                "FactionId": 0,
                "Sector": 794,
                "LocationId": 17409,
                "BuildingType": 18,
                "Quality": 8
            },
            {
                "NameSeed": 18903,
                "FactionId": 0,
                "Sector": 800,
                "LocationId": 17409,
                "BuildingType": 18,
                "Quality": 13
            },
            {
                "NameSeed": 4187,
                "FactionId": 0,
                "Sector": 807,
                "LocationId": 17409,
                "BuildingType": 18,
                "Quality": 18
            },
            {
                "NameSeed": 15116,
                "FactionId": 510,
                "Sector": 812,
                "LocationId": 17409,
                "BuildingType": 15,
                "Quality": 12
            },
            {
                "NameSeed": 14520,
                "FactionId": 0,
                "Sector": 825,
                "LocationId": 17409,
                "BuildingType": 18,
                "Quality": 13
            },
            {
                "NameSeed": 1318,
                "FactionId": 0,
                "Sector": 831,
                "LocationId": 17409,
                "BuildingType": 18,
                "Quality": 19
            },
            {
                "NameSeed": 4275,
                "FactionId": 0,
                "Sector": 836,
                "LocationId": 17409,
                "BuildingType": 18,
                "Quality": 18
            },
            {
                "NameSeed": 7740,
                "FactionId": 0,
                "Sector": 841,
                "LocationId": 17409,
                "BuildingType": 18,
                "Quality": 1
            },
            {
                "NameSeed": 28925,
                "FactionId": 0,
                "Sector": 845,
                "LocationId": 17409,
                "BuildingType": 18,
                "Quality": 19
            },
            {
                "NameSeed": 20651,
                "FactionId": 0,
                "Sector": 856,
                "LocationId": 17409,
                "BuildingType": 18,
                "Quality": 20
            },
            {
                "NameSeed": 499,
                "FactionId": 0,
                "Sector": 862,
                "LocationId": 17409,
                "BuildingType": 18,
                "Quality": 14
            },
            {
                "NameSeed": 21289,
                "FactionId": 0,
                "Sector": 869,
                "LocationId": 17409,
                "BuildingType": 18,
                "Quality": 19
            },
            {
                "NameSeed": 29764,
                "FactionId": 0,
                "Sector": 875,
                "LocationId": 17409,
                "BuildingType": 18,
                "Quality": 17
            },
            {
                "NameSeed": 5205,
                "FactionId": 0,
                "Sector": 878,
                "LocationId": 17409,
                "BuildingType": 18,
                "Quality": 3
            },
            {
                "NameSeed": 30035,
                "FactionId": 0,
                "Sector": 886,
                "LocationId": 17409,
                "BuildingType": 18,
                "Quality": 4
            },
            {
                "NameSeed": 3965,
                "FactionId": 0,
                "Sector": 893,
                "LocationId": 17409,
                "BuildingType": 18,
                "Quality": 3
            },
            {
                "NameSeed": 594,
                "FactionId": 0,
                "Sector": 898,
                "LocationId": 17409,
                "BuildingType": 18,
                "Quality": 11
            },
            {
                "NameSeed": 19350,
                "FactionId": 510,
                "Sector": 903,
                "LocationId": 17409,
                "BuildingType": 9,
                "Quality": 16
            },
            {
                "NameSeed": 25198,
                "FactionId": 510,
                "Sector": 906,
                "LocationId": 17409,
                "BuildingType": 9,
                "Quality": 18
            },
            {
                "NameSeed": 380,
                "FactionId": 510,
                "Sector": 917,
                "LocationId": 17409,
                "BuildingType": 9,
                "Quality": 7
            }
        ],
        "ExteriorData": {
            "AnotherName": "Knightspath",
            "MapId": 760000000293,
            "LocationId": 0,
            "Width": 4,
            "Height": 3,
            "PortTownAndUnknown": 0,
            "BlockNames": [
                "FILLAA13.RMB",
                "GRVEAM42.RMB",
                "RESIAM05.RMB",
                "DARKAA01.RMB",
                "THIEAM00.RMB",
                "RESIAM04.RMB",
                "TVRNAM07.RMB",
                "GENRAM02.RMB",
                "GENRAM02.RMB",
                "BOOKAM01.RMB",
                "FIGHAA01.RMB",
                "GENRAM00.RMB"
            ]
        }
    },
    "Dungeon": {
        "RecordElement": {
            "Header": {
                "X": 0,
                "Y": 0,
                "IsExterior": 0,
                "Unknown2": 0,
                "LocationId": 0,
                "IsInterior": 0,
                "ExteriorLocationId": 0,
                "LocationName": null
            }
        },
        "Header": {
            "BlockCount": 0
        },
        "Blocks": null
    },
    "Climate": {
        "WorldClimate": 230,
        "ClimateType": 300,
        "NatureSet": 506,
        "GroundArchive": 102,
        "NatureArchive": 506,
        "SkyBase": 16,
        "People": 3,
        "Names": 0
    },
    "Politic": 186,
    "RegionIndex": 58,
    "LocationIndex": 34
}