{
    "Loaded": true,
    "Name": "Wailing Light of Kynareth",
    "RegionName": "Wrothgarian Mountains",
    "HasDungeon": false,
    "MapTableData": {
        "MapId": 578000000840,
        "Latitude": 45224,
        "Longitude": 107560,
        "LocationType": 5,
        "DungeonType": 255,
        "Discovered": true,
        "Key": 16
    },
    "Exterior": {
        "RecordElement": {
            "Header": {
                "X": 27539456,
                "Y": 18954241,
                "IsExterior": 32768,
                "Unknown2": 129,
                "LocationId": 10446,
                "IsInterior": 0,
                "ExteriorLocationId": 0,
                "LocationName": "Wailing Light of Kynareth"
            }
        },
        "BuildingCount": 14,
        "Buildings": [
            {
                "NameSeed": 17475,
                "FactionId": 0,
                "Sector": 4,
                "LocationId": 10446,
                "BuildingType": 18,
                "Quality": 1
            },
            {
                "NameSeed": 21979,
                "FactionId": 0,
                "Sector": 9,
                "LocationId": 10446,
                "BuildingType": 18,
                "Quality": 13
            },
            {
                "NameSeed": 10288,
                "FactionId": 0,
                "Sector": 15,
                "LocationId": 10446,
                "BuildingType": 19,
                "Quality": 10
            },
            {
                "NameSeed": 7223,
                "FactionId": 0,
                "Sector": 20,
                "LocationId": 10446,
                "BuildingType": 18,
                "Quality": 4
            },
            {
                "NameSeed": 24317,
                "FactionId": 0,
                "Sector": 23,
                "LocationId": 10446,
                "BuildingType": 18,
                "Quality": 10
            },
            {
                "NameSeed": 2807,
                "FactionId": 0,
                "Sector": 31,
                "LocationId": 10446,
                "BuildingType": 18,
                "Quality": 12
            },
            {
                "NameSeed": 18632,
                "FactionId": 0,
                "Sector": 35,
                "LocationId": 10446,
                "BuildingType": 19,
                "Quality": 6
            },
            {
                "NameSeed": 24125,
                "FactionId": 0,
                "Sector": 41,
                "LocationId": 10446,
                "BuildingType": 18,
                "Quality": 14
            },
            {
                "NameSeed": 10140,
                "FactionId": 0,
                "Sector": 47,
                "LocationId": 10446,
                "BuildingType": 18,
                "Quality": 1
            },
            {
                "NameSeed": 25599,
                "FactionId": 0,
                "Sector": 50,
                "LocationId": 10446,
                "BuildingType": 18,
                "Quality": 1
            },
            {
                "NameSeed": 3772,
                "FactionId": 0,
                "Sector": 60,
                "LocationId": 10446,
                "BuildingType": 18,
                "Quality": 15
            },
            {
                "NameSeed": 28110,
                "FactionId": 0,
                "Sector": 68,
                "LocationId": 10446,
                "BuildingType": 18,
                "Quality": 10
            },
            {
                "NameSeed": 20905,
                "FactionId": 0,
                "Sector": 72,
                "LocationId": 10446,
                "BuildingType": 18,
                "Quality": 15
            },
            {
                "NameSeed": 16566,
                "FactionId": 35,
                "Sector": 78,
                "LocationId": 10446,
                "BuildingType": 14,
                "Quality": 8
            }
        ],
        "ExteriorData": {
            "AnotherName": "Wailing Light of Kynareth",
            "MapId": 578000000840,
            "LocationId": 0,
            "Width": 1,
            "Height": 1,
            "PortTownAndUnknown": 0,
            "BlockNames": [
                "TEMPAAH0.RMB"
            ]
        }
    },
    "Dungeon": {
        "RecordElement": {
            "Header": {
                "X": 0,
                "Y": 0,
                "IsExterior": 0,
                "Unknown2": 0,
                "LocationId": 0,
                "IsInterior": 0,
                "ExteriorLocationId": 0,
                "LocationName": null
            }
        },
        "Header": {
            "BlockCount": 0
        },
        "Blocks": null
    },
    "Climate": {
        "WorldClimate": 226,
        "ClimateType": 100,
        "NatureSet": 510,
        "GroundArchive": 102,
        "NatureArchive": 510,
        "SkyBase": 0,
        "People": 0,
        "Names": 0
    },
    "Politic": 144,
    "RegionIndex": 16,
    "LocationIndex": 1728
}