{
    "Loaded": true,
    "Name": "The Coppersly Crypts",
    "RegionName": "Menevia",
    "HasDungeon": true,
    "MapTableData": {
        "MapId": 358000000897,
        "Latitude": 73384,
        "Longitude": 114856,
        "LocationType": 12,
        "DungeonType": 18,
        "Discovered": true,
        "Key": 0
    },
    "Exterior": {
        "RecordElement": {
            "Header": {
                "X": 29407232,
                "Y": 11745281,
                "IsExterior": 32768,
                "Unknown2": 75,
                "LocationId": 20009,
                "IsInterior": 0,
                "ExteriorLocationId": 0,
                "LocationName": "The Coppersly Crypts"
            }
        },
        "BuildingCount": 0,
        "Buildings": [],
        "ExteriorData": {
            "AnotherName": "The Coppersly Crypts",
            "MapId": 358000000897,
            "LocationId": 0,
            "Width": 1,
            "Height": 1,
            "PortTownAndUnknown": 0,
            "BlockNames": [
                "GRVEAS39.RMB"
            ]
        }
    },
    "Dungeon": {
        "RecordElement": {
            "Header": {
                "X": 27768832,
                "Y": 10729473,
                "IsExterior": 0,
                "Unknown2": 12,
                "LocationId": 20010,
                "IsInterior": 1,
                "ExteriorLocationId": 20009,
                "LocationName": "The Coppersly Crypts"
            }
        },
        "Header": {
            "BlockCount": 5
        },
        "Blocks": [
            {
                "X": -1,
                "Z": 0,
                "IsStartingBlock": false,
                "BlockName": "B0000004.RDB",
                "WaterLevel": 0,
                "CastleBlock": false
            },
            {
                "X": 0,
                "Z": -1,
                "IsStartingBlock": false,
                "BlockName": "B0000003.RDB",
                "WaterLevel": 0,
                "CastleBlock": false
            },
            {
                "X": 0,
                "Z": 0,
                "IsStartingBlock": true,
                "BlockName": "M0000001.RDB",
                "WaterLevel": 0,
                "CastleBlock": false
            },
            {
                "X": 0,
                "Z": 1,
                "IsStartingBlock": false,
                "BlockName": "B0000014.RDB",
                "WaterLevel": 0,
                "CastleBlock": false
            },
            {
                "X": 1,
                "Z": 0,
                "IsStartingBlock": false,
                "BlockName": "B0000012.RDB",
                "WaterLevel": 0,
                "CastleBlock": false
            }
        ]
    },
    "Climate": {
        "WorldClimate": 231,
        "ClimateType": 300,
        "NatureSet": 504,
        "GroundArchive": 302,
        "NatureArchive": 504,
        "SkyBase": 16,
        "People": 3,
        "Names": 0
    },
    "Politic": 161,
    "RegionIndex": 33,
    "LocationIndex": 95
}